terryology/__init__.py
terryology/core.py
terryology-0.1.3.dist-info/METADATA
terryology-0.1.3.dist-info/WHEEL
terryology-0.1.3.dist-info/licenses/LICENSE
terryology-0.1.3.dist-info/RECORD
