Metadata-Version: 2.4
Name: terryology
Version: 0.1.3
Summary: A Python package implementing Terry's unique mathematical system
Project-URL: Homepage, https://github.com/Shtzkrieg/to
Project-URL: Repository, https://github.com/Shtzkrieg/to.git
Author: Caleb Hopkins
License-Expression: MIT
License-File: LICENSE
Keywords: education,mathematics,terryology
Classifier: Development Status :: 3 - Alpha
Classifier: Intended Audience :: Education
Classifier: License :: OSI Approved :: MIT License
Classifier: Programming Language :: Python :: 3
Classifier: Programming Language :: Python :: 3.8
Classifier: Programming Language :: Python :: 3.9
Classifier: Programming Language :: Python :: 3.10
Classifier: Programming Language :: Python :: 3.11
Classifier: Programming Language :: Python :: 3.12
Requires-Python: >=3.8
